aiomas/__init__.py
aiomas/agent.py
aiomas/channel.py
aiomas/clocks.py
aiomas/codecs.py
aiomas/exceptions.py
aiomas/local_queue.py
aiomas/rpc.py
aiomas/subproc.py
aiomas/util.py
aiomas-2.0.1.dist-info/DESCRIPTION.rst
aiomas-2.0.1.dist-info/METADATA
aiomas-2.0.1.dist-info/RECORD
aiomas-2.0.1.dist-info/WHEEL
aiomas-2.0.1.dist-info/entry_points.txt
aiomas-2.0.1.dist-info/metadata.json
aiomas-2.0.1.dist-info/top_level.txt
