Metadata-Version: 2.0
Name: aiomas
Version: 2.0.1
Summary: Asyncio-based, layered networking library providing request-reply channels, RPC, and multi-agent systems.
Home-page: https://aiomas.readthedocs.io
Author: Stefan Scherfke
Author-email: stefan@sofa-rockers.org
License: UNKNOWN
Platform: UNKNOWN
Classifier: Development Status :: 5 - Production/Stable
Classifier: Environment :: Console
Classifier: Intended Audience :: Science/Research
Classifier: License :: OSI Approved :: MIT License
Classifier: Natural Language :: English
Classifier: Operating System :: OS Independent
Classifier: Programming Language :: Python
Classifier: Programming Language :: Python :: 3
Classifier: Programming Language :: Python :: 3.5
Classifier: Programming Language :: Python :: 3.6
Classifier: Programming Language :: Python :: 3 :: Only
Classifier: Programming Language :: Python :: Implementation :: CPython
Classifier: Programming Language :: Python :: Implementation :: PyPy
Classifier: Topic :: Scientific/Engineering
Classifier: Topic :: Software Development :: Libraries :: Python Modules
Requires-Python: >=3.5
Requires-Dist: arrow (>=0.7)
Provides-Extra: mp
Requires-Dist: msgpack-python (>=0.4.7); extra == 'mp'
Provides-Extra: mpb
Requires-Dist: blosc (>=1.3.2); extra == 'mpb'
Requires-Dist: msgpack-python (>=0.4.7); extra == 'mpb'
